reti_logiche/esami/verilog/2023-01-10/abc.v
module ABC(
  soc, eoc, x,
  rfd1, rfd2, rfd3, 
  dav1_, dav2_, dav3_,
  c1, c2, c3,
  clock, reset_,
);
  input reset_, clock;

  input eoc;
  input rfd1, rfd2, rfd3;
  input[7:0] x;

  output soc;
  output dav1_, dav2_, dav3_;
  output[2:0] c1, c2, c3;

  reg SOC; 
  assign soc = SOC;
  reg DAV_;
  assign dav1_ = DAV_;
  assign dav2_ = DAV_;
  assign dav3_ = DAV_;

  reg[2:0] C;
  assign c1 = C; 
  assign c2 = C; 
  assign c3 = C; 

  reg[7:0] X;

  reg[2:0] STAR;
  localparam S0 = 0,
             S1 = 1,
             S2 = 2,
             S3 = 3,
             S4 = 4;

  always @(reset_ == 0) begin
    STAR <= S0;
    DAV_ <= 1;
    SOC <= 0;
  end


  always @(posedge clock) if (reset_ == 1) begin
    casex (STAR)
      S0: begin
        SOC <= 1;
        STAR <= (eoc == 0) ? S1 : S0;
      end 
      S1: begin
        SOC <= 0; 
        C <= 0;
        X <= x;
        STAR <= (eoc == 1) ? S2 : S1;
      end
      S2: begin
        C <= C + X[0];
        X <= {2'b00, X[7:2]};
        STAR <= (X == 0) ? S3 : S2;
      end
      S3: begin
        DAV_ <= 0;
        STAR <= ({rfd1, rfd2, rfd3} == 3'b000) ? S4 : S3;
      end
      S4: begin
        DAV_ = 1;
        STAR <= ({rfd2, rfd2, rfd3} == 3'b111) ? S0: S4;
      end
    endcase
  end


endmodule

reti_logiche/esami/verilog/2023-01-10/testbench.v
module testbench();

    wire clock;

    clock_generator clk(
        .clock(clock)
    );

    reg reset_;

    reg [7:0] x;
    reg eoc;
    wire soc;

    wire [2:0] c1;
    reg rfd1;
    wire dav1_;

    wire [2:0] c2;
    reg rfd2;
    wire dav2_;

    wire [2:0] c3;
    reg rfd3;
    wire dav3_;

    ABC dut (
        .x(x), .soc(soc), .eoc(eoc), 
        .c1(c1), .rfd1(rfd1), .dav1_(dav1_),
        .c2(c2), .rfd2(rfd2), .dav2_(dav2_),
        .c3(c3), .rfd3(rfd3), .dav3_(dav3_),
        .clock(clock), .reset_(reset_)
    );

    initial begin
        $dumpfile("waveform.vcd");
        $dumpvars;

        //the following structure is used to wait for expected signals, and fail if too much time passes
        fork : f
            begin
                #100000;
                $display("Timeout - waiting for signal failed");
                disable f;
            end
        //actual tests start here
            begin
                eoc = 1;
                rfd1 = 1; rfd2 = 1; rfd3 = 1;

                //reset phase
                reset_ = 0; #(clk.HALF_PERIOD);
                
                //first posedge
                reset_ = 1;

                if(soc !== 0)
                    $display("soc is not 0 after reset");

                if(dav1_ !== 1)
                    $display("dav1_ is not 1 after reset");
                if(dav2_ !== 1)
                    $display("dav2_ is not 1 after reset");
                if(dav3_ !== 1)
                    $display("dav3_ is not 1 after reset");

                fork
                    // Producer
                    begin : producer
                        reg [4:0] i;
                        reg [7:0] v;
                        reg [2:0] c;

                        for (i = 0; i < 16; i++) begin
                            {v, c} = get_testcase(i);
                            
                            @(posedge soc);
                            #(2*clk.HALF_PERIOD); 
                            eoc = 0;
                            @(negedge soc);
                            #(2*clk.HALF_PERIOD); 
                            x = v;
                            #(2*clk.HALF_PERIOD); 
                            eoc = 1;    
                        end
                    end
                    //Consumer 1
                    begin : consumer_1
                        reg [4:0] i;
                        reg [7:0] v;
                        reg [2:0] c;

                        for (i = 0; i < 16; i++) begin
                            {v, c} = get_testcase(i);

                            @(negedge dav1_);
                            if(c1 !== c) begin
                                error = 1;
                                $display("C1: Test #%g failed, expected %g, got %g", i, c, c1);
                            end
                            #(1*2*clk.HALF_PERIOD); 
                            rfd1 = 0;
                            @(posedge dav1_);
                            #(1*2*clk.HALF_PERIOD); 
                            rfd1 = 1;
                        end
                    end
                    //Consumer 2
                    begin : consumer_2
                        reg [4:0] i;
                        reg [7:0] v;
                        reg [2:0] c;

                        for (i = 0; i < 16; i++) begin
                            {v, c} = get_testcase(i);

                            @(negedge dav2_);
                            if(c2 !== c) begin
                                error = 1;
                                $display("C2: Test #%g failed, expected %g, got %g", i, c, c2);
                            end
                            #(2*2*clk.HALF_PERIOD); 
                            rfd2 = 0;
                            @(posedge dav2_);
                            #(2*2*clk.HALF_PERIOD); 
                            rfd2 = 1;
                        end
                    end
                    //Consumer 3
                    begin : consumer_3
                        reg [4:0] i;
                        reg [7:0] v;
                        reg [2:0] c;

                        for (i = 0; i < 16; i++) begin
                            {v, c} = get_testcase(i);

                            @(negedge dav3_);
                            if(c3 !== c) begin
                                error = 1;
                                $display("C3: Test #%g failed, expected %g, got %g", i, c, c3);
                            end
                            #(3*2*clk.HALF_PERIOD); 
                            rfd3 = 0;
                            @(posedge dav3_);
                            #(3*2*clk.HALF_PERIOD); 
                            rfd3 = 1;
                        end
                    end
                join

                #10;
                disable f;
            end
        join

        $finish;
    end

    // linea di errore, utile per il debug
    reg error;
    initial error = 0;
    always @(posedge error) #1
        error = 0;

    function automatic [15:0] get_testcase;
        input [4:0] i;

        reg [7:0] v;
        reg [2:0] c;

        begin
            v[7:4] = i * 5;
            v[3:0] = i * 7;

            c = 0;
            if(v[6] == 1)
                c += 1;
            if(v[4] == 1)
                c += 1;
            if(v[2] == 1)
                c += 1;
            if(v[0] == 1)
                c += 1;

            get_testcase = {v, c};
        end
    endfunction

endmodule

// generatore del segnale di clock
module clock_generator(
    clock
);
    output clock;

    parameter HALF_PERIOD = 5;

    reg CLOCK;
    assign clock = CLOCK;

    initial CLOCK <= 0;
    always #HALF_PERIOD CLOCK <= ~CLOCK;

endmodule

reti_logiche/esami/verilog/2023-01-10/waveform.vcd
$date
	Thu May 29 18:57:08 2025
$end
$version
	Icarus Verilog
$end
$timescale
	1s
$end
$scope module testbench $end
$var wire 1 ! soc $end
$var wire 1 " dav3_ $end
$var wire 1 # dav2_ $end
$var wire 1 $ dav1_ $end
$var wire 1 % clock $end
$var wire 3 & c3 [2:0] $end
$var wire 3 ' c2 [2:0] $end
$var wire 3 ( c1 [2:0] $end
$var reg 1 ) eoc $end
$var reg 1 * error $end
$var reg 1 + reset_ $end
$var reg 1 , rfd1 $end
$var reg 1 - rfd2 $end
$var reg 1 . rfd3 $end
$var reg 8 / x [7:0] $end
$scope function get_testcase $end
$upscope $end
$scope module clk $end
$var wire 1 % clock $end
$var parameter 32 0 HALF_PERIOD $end
$var reg 1 1 CLOCK $end
$upscope $end
$scope module dut $end
$var wire 3 2 c1 [2:0] $end
$var wire 3 3 c2 [2:0] $end
$var wire 3 4 c3 [2:0] $end
$var wire 1 % clock $end
$var wire 1 $ dav1_ $end
$var wire 1 # dav2_ $end
$var wire 1 " dav3_ $end
$var wire 1 ) eoc $end
$var wire 1 + reset_ $end
$var wire 1 , rfd1 $end
$var wire 1 - rfd2 $end
$var wire 1 . rfd3 $end
$var wire 1 ! soc $end
$var wire 8 5 x [7:0] $end
$var parameter 32 6 S0 $end
$var parameter 32 7 S1 $end
$var parameter 32 8 S2 $end
$var parameter 32 9 S3 $end
$var parameter 32 : S4 $end
$var reg 3 ; C [2:0] $end
$var reg 1 < DAV_ $end
$var reg 1 = SOC $end
$var reg 3 > STAR [2:0] $end
$var reg 8 ? X [7:0] $end
$upscope $end
$scope fork f $end
$scope begin consumer_1 $end
$var reg 3 @ c [2:0] $end
$var reg 5 A i [4:0] $end
$var reg 8 B v [7:0] $end
$upscope $end
$scope begin consumer_2 $end
$var reg 3 C c [2:0] $end
$var reg 5 D i [4:0] $end
$var reg 8 E v [7:0] $end
$upscope $end
$scope begin consumer_3 $end
$var reg 3 F c [2:0] $end
$var reg 5 G i [4:0] $end
$var reg 8 H v [7:0] $end
$upscope $end
$scope begin producer $end
$var reg 3 I c [2:0] $end
$var reg 5 J i [4:0] $end
$var reg 8 K v [7:0] $end
$upscope $end
$upscope $end
$upscope $end
$enddefinitions $end
$comment Show the parameter values. $end
$dumpall
b100 :
b11 9
b10 8
b1 7
b0 6
b101 0
$end
#0
$dumpvars
bx K
bx J
bx I
bx H
bx G
bx F
bx E
bx D
bx C
bx B
bx A
bx @
bx ?
b0 >
0=
1<
bx ;
bx 5
bx 4
bx 3
bx 2
01
bx /
1.
1-
1,
0+
0*
1)
bx (
bx '
bx &
0%
1$
1#
1"
0!
$end
#5
1!
1=
1%
11
b0 K
b0 I
b0 J
b0 B
b0 @
b0 A
b0 E
b0 C
b0 D
b0 H
b0 F
b0 G
1+
#10
0%
01
#15
b1 >
1%
11
0)
#20
0%
01
#25
b0 &
b0 4
b0 '
b0 3
b0 (
b0 2
b0 ;
0!
0=
1%
11
#30
0%
01
#35
b0 ?
1%
11
b0 /
b0 5
#40
0%
01
#45
b10 >
1%
11
b1010111 K
b100 I
b1 J
1)
#50
0%
01
#55
b11 >
1%
11
#60
0%
01
#65
0"
0#
0$
0<
1%
11
#70
0%
01
#75
1%
11
0,
#80
0%
01
#85
1%
11
0-
#90
0%
01
#95
b100 >
1%
11
0.
#100
0%
01
#105
1"
1#
1$
1<
1%
11
#110
0%
01
#115
1%
11
b1010111 B
b100 @
b1 A
1,
#120
0%
01
#125
1%
11
b1010111 E
b100 C
b1 D
1-
#130
0%
01
#135
b0 >
1%
11
b1010111 H
b100 F
b1 G
1.
#140
0%
01
#145
1!
1=
1%
11
#150
0%
01
#155
b1 >
1%
11
0)
#160
0%
01
#165
0!
0=
1%
11
#170
0%
01
#175
b1010111 ?
1%
11
b1010111 /
b1010111 5
#180
0%
01
#185
b10 >
1%
11
b10101110 K
b1 I
b10 J
1)
#190
0%
01
#195
b10101 ?
b1 &
b1 4
b1 '
b1 3
b1 (
b1 2
b1 ;
1%
11
#200
0%
01
#205
b101 ?
b10 &
b10 4
b10 '
b10 3
b10 (
b10 2
b10 ;
1%
11
#210
0%
01
#215
b1 ?
b11 &
b11 4
b11 '
b11 3
b11 (
b11 2
b11 ;
1%
11
#220
0%
01
#225
b0 ?
b100 &
b100 4
b100 '
b100 3
b100 (
b100 2
b100 ;
1%
11
#230
0%
01
#235
b11 >
1%
11
#240
0%
01
#245
0"
0#
0$
0<
1%
11
#250
0%
01
#255
1%
11
0,
#260
0%
01
#265
1%
11
0-
#270
0%
01
#275
b100 >
1%
11
0.
#280
0%
01
#285
1"
1#
1$
1<
1%
11
#290
0%
01
#295
1%
11
b10101110 B
b1 @
b10 A
1,
#300
0%
01
#305
1%
11
b10101110 E
b1 C
b10 D
1-
#310
0%
01
#315
b0 >
1%
11
b10101110 H
b1 F
b10 G
1.
#320
0%
01
#325
1!
1=
1%
11
#330
0%
01
#335
b1 >
1%
11
0)
#340
0%
01
#345
b1010111 ?
b0 &
b0 4
b0 '
b0 3
b0 (
b0 2
b0 ;
0!
0=
1%
11
#350
0%
01
#355
b10101110 ?
1%
11
b10101110 /
b10101110 5
#360
0%
01
#365
b10 >
1%
11
b11110101 K
b100 I
b11 J
1)
#370
0%
01
#375
b101011 ?
1%
11
#380
0%
01
#385
b1010 ?
b1 &
b1 4
b1 '
b1 3
b1 (
b1 2
b1 ;
1%
11
#390
0%
01
#395
b10 ?
1%
11
#400
0%
01
#405
b0 ?
1%
11
#410
0%
01
#415
b11 >
1%
11
#420
0%
01
#425
0"
0#
0$
0<
1%
11
#430
0%
01
#435
1%
11
0,
#440
0%
01
#445
1%
11
0-
#450
0%
01
#455
b100 >
1%
11
0.
#460
0%
01
#465
1"
1#
1$
1<
1%
11
#470
0%
01
#475
1%
11
b11110101 B
b100 @
b11 A
1,
#480
0%
01
#485
1%
11
b11110101 E
b100 C
b11 D
1-
#490
0%
01
#495
b0 >
1%
11
b11110101 H
b100 F
b11 G
1.
#500
0%
01
#505
1!
1=
1%
11
#510
0%
01
#515
b1 >
1%
11
0)
#520
0%
01
#525
b10101110 ?
b0 &
b0 4
b0 '
b0 3
b0 (
b0 2
b0 ;
0!
0=
1%
11
#530
0%
01
#535
b11110101 ?
1%
11
b11110101 /
b11110101 5
#540
0%
01
#545
b10 >
1%
11
b1001100 K
b10 I
b100 J
1)
#550
0%
01
#555
b111101 ?
b1 &
b1 4
b1 '
b1 3
b1 (
b1 2
b1 ;
1%
11
#560
0%
01
#565
b1111 ?
b10 &
b10 4
b10 '
b10 3
b10 (
b10 2
b10 ;
1%
11
#570
0%
01
#575
b11 ?
b11 &
b11 4
b11 '
b11 3
b11 (
b11 2
b11 ;
1%
11
#580
0%
01
#585
b0 ?
b100 &
b100 4
b100 '
b100 3
b100 (
b100 2
b100 ;
1%
11
#590
0%
01
#595
b11 >
1%
11
#600
0%
01
#605
0"
0#
0$
0<
1%
11
#610
0%
01
#615
1%
11
0,
#620
0%
01
#625
1%
11
0-
#630
0%
01
#635
b100 >
1%
11
0.
#640
0%
01
#645
1"
1#
1$
1<
1%
11
#650
0%
01
#655
1%
11
b1001100 B
b10 @
b100 A
1,
#660
0%
01
#665
1%
11
b1001100 E
b10 C
b100 D
1-
#670
0%
01
#675
b0 >
1%
11
b1001100 H
b10 F
b100 G
1.
#680
0%
01
#685
1!
1=
1%
11
#690
0%
01
#695
b1 >
1%
11
0)
#700
0%
01
#705
b11110101 ?
b0 &
b0 4
b0 '
b0 3
b0 (
b0 2
b0 ;
0!
0=
1%
11
#710
0%
01
#715
b1001100 ?
1%
11
b1001100 /
b1001100 5
#720
0%
01
#725
b10 >
1%
11
b10010011 K
b101 J
1)
#730
0%
01
#735
b10011 ?
1%
11
#740
0%
01
#745
b100 ?
b1 &
b1 4
b1 '
b1 3
b1 (
b1 2
b1 ;
1%
11
#750
0%
01
#755
b1 ?
1%
11
#760
0%
01
#765
b0 ?
b10 &
b10 4
b10 '
b10 3
b10 (
b10 2
b10 ;
1%
11
#770
0%
01
#775
b11 >
1%
11
#780
0%
01
#785
0"
0#
0$
0<
1%
11
#790
0%
01
#795
1%
11
0,
#800
0%
01
#805
1%
11
0-
#810
0%
01
#815
b100 >
1%
11
0.
#820
0%
01
#825
1"
1#
1$
1<
1%
11
#830
0%
01
#835
1%
11
b10010011 B
b101 A
1,
#840
0%
01
#845
1%
11
b10010011 E
b101 D
1-
#850
0%
01
#855
b0 >
1%
11
b10010011 H
b101 G
1.
#860
0%
01
#865
1!
1=
1%
11
#870
0%
01
#875
b1 >
1%
11
0)
#880
0%
01
#885
b1001100 ?
b0 &
b0 4
b0 '
b0 3
b0 (
b0 2
b0 ;
0!
0=
1%
11
#890
0%
01
#895
b10010011 ?
1%
11
b10010011 /
b10010011 5
#900
0%
01
#905
b10 >
1%
11
b11101010 K
b1 I
b110 J
1)
#910
0%
01
#915
b100100 ?
b1 &
b1 4
b1 '
b1 3
b1 (
b1 2
b1 ;
1%
11
#920
0%
01
#925
b1001 ?
1%
11
#930
0%
01
#935
b10 ?
b10 &
b10 4
b10 '
b10 3
b10 (
b10 2
b10 ;
1%
11
#940
0%
01
#945
b0 ?
1%
11
#950
0%
01
#955
b11 >
1%
11
#960
0%
01
#965
0"
0#
0$
0<
1%
11
#970
0%
01
#975
1%
11
0,
#980
0%
01
#985
1%
11
0-
#990
0%
01
#995
b100 >
1%
11
0.
#1000
0%
01
#1005
1"
1#
1$
1<
1%
11
#1010
0%
01
#1015
1%
11
b11101010 B
b1 @
b110 A
1,
#1020
0%
01
#1025
1%
11
b11101010 E
b1 C
b110 D
1-
#1030
0%
01
#1035
b0 >
1%
11
b11101010 H
b1 F
b110 G
1.
#1040
0%
01
#1045
1!
1=
1%
11
#1050
0%
01
#1055
b1 >
1%
11
0)
#1060
0%
01
#1065
b10010011 ?
b0 &
b0 4
b0 '
b0 3
b0 (
b0 2
b0 ;
0!
0=
1%
11
#1070
0%
01
#1075
b11101010 ?
1%
11
b11101010 /
b11101010 5
#1080
0%
01
#1085
b10 >
1%
11
b110001 K
b10 I
b111 J
1)
#1090
0%
01
#1095
b111010 ?
1%
11
#1100
0%
01
#1105
b1110 ?
1%
11
#1110
0%
01
#1115
b11 ?
1%
11
#1120
0%
01
#1125
b0 ?
b1 &
b1 4
b1 '
b1 3
b1 (
b1 2
b1 ;
1%
11
#1130
0%
01
#1135
b11 >
1%
11
#1140
0%
01
#1145
0"
0#
0$
0<
1%
11
#1150
0%
01
#1155
1%
11
0,
#1160
0%
01
#1165
1%
11
0-
#1170
0%
01
#1175
b100 >
1%
11
0.
#1180
0%
01
#1185
1"
1#
1$
1<
1%
11
#1190
0%
01
#1195
1%
11
b110001 B
b10 @
b111 A
1,
#1200
0%
01
#1205
1%
11
b110001 E
b10 C
b111 D
1-
#1210
0%
01
#1215
b0 >
1%
11
b110001 H
b10 F
b111 G
1.
#1220
0%
01
#1225
1!
1=
1%
11
#1230
0%
01
#1235
b1 >
1%
11
0)
#1240
0%
01
#1245
b11101010 ?
b0 &
b0 4
b0 '
b0 3
b0 (
b0 2
b0 ;
0!
0=
1%
11
#1250
0%
01
#1255
b110001 ?
1%
11
b110001 /
b110001 5
#1260
0%
01
#1265
b10 >
1%
11
b10001000 K
b0 I
b1000 J
1)
#1270
0%
01
#1275
b1100 ?
b1 &
b1 4
b1 '
b1 3
b1 (
b1 2
b1 ;
1%
11
#1280
0%
01
#1285
b11 ?
1%
11
#1290
0%
01
#1295
b0 ?
b10 &
b10 4
b10 '
b10 3
b10 (
b10 2
b10 ;
1%
11
#1300
0%
01
#1305
b11 >
1%
11
#1310
0%
01
#1315
0"
0#
0$
0<
1%
11
#1320
0%
01
#1325
1%
11
0,
#1330
0%
01
#1335
1%
11
0-
#1340
0%
01
#1345
b100 >
1%
11
0.
#1350
0%
01
#1355
1"
1#
1$
1<
1%
11
#1360
0%
01
#1365
1%
11
b10001000 B
b0 @
b1000 A
1,
#1370
0%
01
#1375
1%
11
b10001000 E
b0 C
b1000 D
1-
#1380
0%
01
#1385
b0 >
1%
11
b10001000 H
b0 F
b1000 G
1.
#1390
0%
01
#1395
1!
1=
1%
11
#1400
0%
01
#1405
b1 >
1%
11
0)
#1410
0%
01
#1415
b110001 ?
b0 &
b0 4
b0 '
b0 3
b0 (
b0 2
b0 ;
0!
0=
1%
11
#1420
0%
01
#1425
b10001000 ?
1%
11
b10001000 /
b10001000 5
#1430
0%
01
#1435
b10 >
1%
11
b11011111 K
b100 I
b1001 J
1)
#1440
0%
01
#1445
b100010 ?
1%
11
#1450
0%
01
#1455
b1000 ?
1%
11
#1460
0%
01
#1465
b10 ?
1%
11
#1470
0%
01
#1475
b0 ?
1%
11
#1480
0%
01
#1485
b11 >
1%
11
#1490
0%
01
#1495
0"
0#
0$
0<
1%
11
#1500
0%
01
#1505
1%
11
0,
#1510
0%
01
#1515
1%
11
0-
#1520
0%
01
#1525
b100 >
1%
11
0.
#1530
0%
01
#1535
1"
1#
1$
1<
1%
11
#1540
0%
01
#1545
1%
11
b11011111 B
b100 @
b1001 A
1,
#1550
0%
01
#1555
1%
11
b11011111 E
b100 C
b1001 D
1-
#1560
0%
01
#1565
b0 >
1%
11
b11011111 H
b100 F
b1001 G
1.
#1570
0%
01
#1575
1!
1=
1%
11
#1580
0%
01
#1585
b1 >
1%
11
0)
#1590
0%
01
#1595
b10001000 ?
0!
0=
1%
11
#1600
0%
01
#1605
b11011111 ?
1%
11
b11011111 /
b11011111 5
#1610
0%
01
#1615
b10 >
1%
11
b100110 K
b1 I
b1010 J
1)
#1620
0%
01
#1625
b110111 ?
b1 &
b1 4
b1 '
b1 3
b1 (
b1 2
b1 ;
1%
11
#1630
0%
01
#1635
b1101 ?
b10 &
b10 4
b10 '
b10 3
b10 (
b10 2
b10 ;
1%
11
#1640
0%
01
#1645
b11 ?
b11 &
b11 4
b11 '
b11 3
b11 (
b11 2
b11 ;
1%
11
#1650
0%
01
#1655
b0 ?
b100 &
b100 4
b100 '
b100 3
b100 (
b100 2
b100 ;
1%
11
#1660
0%
01
#1665
b11 >
1%
11
#1670
0%
01
#1675
0"
0#
0$
0<
1%
11
#1680
0%
01
#1685
1%
11
0,
#1690
0%
01
#1695
1%
11
0-
#1700
0%
01
#1705
b100 >
1%
11
0.
#1710
0%
01
#1715
1"
1#
1$
1<
1%
11
#1720
0%
01
#1725
1%
11
b100110 B
b1 @
b1010 A
1,
#1730
0%
01
#1735
1%
11
b100110 E
b1 C
b1010 D
1-
#1740
0%
01
#1745
b0 >
1%
11
b100110 H
b1 F
b1010 G
1.
#1750
0%
01
#1755
1!
1=
1%
11
#1760
0%
01
#1765
b1 >
1%
11
0)
#1770
0%
01
#1775
b11011111 ?
b0 &
b0 4
b0 '
b0 3
b0 (
b0 2
b0 ;
0!
0=
1%
11
#1780
0%
01
#1785
b100110 ?
1%
11
b100110 /
b100110 5
#1790
0%
01
#1795
b10 >
1%
11
b1111101 K
b100 I
b1011 J
1)
#1800
0%
01
#1805
b1001 ?
1%
11
#1810
0%
01
#1815
b10 ?
b1 &
b1 4
b1 '
b1 3
b1 (
b1 2
b1 ;
1%
11
#1820
0%
01
#1825
b0 ?
1%
11
#1830
0%
01
#1835
b11 >
1%
11
#1840
0%
01
#1845
0"
0#
0$
0<
1%
11
#1850
0%
01
#1855
1%
11
0,
#1860
0%
01
#1865
1%
11
0-
#1870
0%
01
#1875
b100 >
1%
11
0.
#1880
0%
01
#1885
1"
1#
1$
1<
1%
11
#1890
0%
01
#1895
1%
11
b1111101 B
b100 @
b1011 A
1,
#1900
0%
01
#1905
1%
11
b1111101 E
b100 C
b1011 D
1-
#1910
0%
01
#1915
b0 >
1%
11
b1111101 H
b100 F
b1011 G
1.
#1920
0%
01
#1925
1!
1=
1%
11
#1930
0%
01
#1935
b1 >
1%
11
0)
#1940
0%
01
#1945
b100110 ?
b0 &
b0 4
b0 '
b0 3
b0 (
b0 2
b0 ;
0!
0=
1%
11
#1950
0%
01
#1955
b1111101 ?
1%
11
b1111101 /
b1111101 5
#1960
0%
01
#1965
b10 >
1%
11
b11000100 K
b10 I
b1100 J
1)
#1970
0%
01
#1975
b11111 ?
b1 &
b1 4
b1 '
b1 3
b1 (
b1 2
b1 ;
1%
11
#1980
0%
01
#1985
b111 ?
b10 &
b10 4
b10 '
b10 3
b10 (
b10 2
b10 ;
1%
11
#1990
0%
01
#1995
b1 ?
b11 &
b11 4
b11 '
b11 3
b11 (
b11 2
b11 ;
1%
11
#2000
0%
01
#2005
b0 ?
b100 &
b100 4
b100 '
b100 3
b100 (
b100 2
b100 ;
1%
11
#2010
0%
01
#2015
b11 >
1%
11
#2020
0%
01
#2025
0"
0#
0$
0<
1%
11
#2030
0%
01
#2035
1%
11
0,
#2040
0%
01
#2045
1%
11
0-
#2050
0%
01
#2055
b100 >
1%
11
0.
#2060
0%
01
#2065
1"
1#
1$
1<
1%
11
#2070
0%
01
#2075
1%
11
b11000100 B
b10 @
b1100 A
1,
#2080
0%
01
#2085
1%
11
b11000100 E
b10 C
b1100 D
1-
#2090
0%
01
#2095
b0 >
1%
11
b11000100 H
b10 F
b1100 G
1.
#2100
0%
01
#2105
1!
1=
1%
11
#2110
0%
01
#2115
b1 >
1%
11
0)
#2120
0%
01
#2125
b1111101 ?
b0 &
b0 4
b0 '
b0 3
b0 (
b0 2
b0 ;
0!
0=
1%
11
#2130
0%
01
#2135
b11000100 ?
1%
11
b11000100 /
b11000100 5
#2140
0%
01
#2145
b10 >
1%
11
b11011 K
b1101 J
1)
#2150
0%
01
#2155
b110001 ?
1%
11
#2160
0%
01
#2165
b1100 ?
b1 &
b1 4
b1 '
b1 3
b1 (
b1 2
b1 ;
1%
11
#2170
0%
01
#2175
b11 ?
1%
11
#2180
0%
01
#2185
b0 ?
b10 &
b10 4
b10 '
b10 3
b10 (
b10 2
b10 ;
1%
11
#2190
0%
01
#2195
b11 >
1%
11
#2200
0%
01
#2205
0"
0#
0$
0<
1%
11
#2210
0%
01
#2215
1%
11
0,
#2220
0%
01
#2225
1%
11
0-
#2230
0%
01
#2235
b100 >
1%
11
0.
#2240
0%
01
#2245
1"
1#
1$
1<
1%
11
#2250
0%
01
#2255
1%
11
b11011 B
b1101 A
1,
#2260
0%
01
#2265
1%
11
b11011 E
b1101 D
1-
#2270
0%
01
#2275
b0 >
1%
11
b11011 H
b1101 G
1.
#2280
0%
01
#2285
1!
1=
1%
11
#2290
0%
01
#2295
b1 >
1%
11
0)
#2300
0%
01
#2305
b11000100 ?
b0 &
b0 4
b0 '
b0 3
b0 (
b0 2
b0 ;
0!
0=
1%
11
#2310
0%
01
#2315
b11011 ?
1%
11
b11011 /
b11011 5
#2320
0%
01
#2325
b10 >
1%
11
b1100010 K
b1 I
b1110 J
1)
#2330
0%
01
#2335
b110 ?
b1 &
b1 4
b1 '
b1 3
b1 (
b1 2
b1 ;
1%
11
#2340
0%
01
#2345
b1 ?
1%
11
#2350
0%
01
#2355
b0 ?
b10 &
b10 4
b10 '
b10 3
b10 (
b10 2
b10 ;
1%
11
#2360
0%
01
#2365
b11 >
1%
11
#2370
0%
01
#2375
0"
0#
0$
0<
1%
11
#2380
0%
01
#2385
1%
11
0,
#2390
0%
01
#2395
1%
11
0-
#2400
0%
01
#2405
b100 >
1%
11
0.
#2410
0%
01
#2415
1"
1#
1$
1<
1%
11
#2420
0%
01
#2425
1%
11
b1100010 B
b1 @
b1110 A
1,
#2430
0%
01
#2435
1%
11
b1100010 E
b1 C
b1110 D
1-
#2440
0%
01
#2445
b0 >
1%
11
b1100010 H
b1 F
b1110 G
1.
#2450
0%
01
#2455
1!
1=
1%
11
#2460
0%
01
#2465
b1 >
1%
11
0)
#2470
0%
01
#2475
b11011 ?
b0 &
b0 4
b0 '
b0 3
b0 (
b0 2
b0 ;
0!
0=
1%
11
#2480
0%
01
#2485
b1100010 ?
1%
11
b1100010 /
b1100010 5
#2490
0%
01
#2495
b10 >
1%
11
b10111001 K
b10 I
b1111 J
1)
#2500
0%
01
#2505
b11000 ?
1%
11
#2510
0%
01
#2515
b110 ?
1%
11
#2520
0%
01
#2525
b1 ?
1%
11
#2530
0%
01
#2535
b0 ?
b1 &
b1 4
b1 '
b1 3
b1 (
b1 2
b1 ;
1%
11
#2540
0%
01
#2545
b11 >
1%
11
#2550
0%
01
#2555
0"
0#
0$
0<
1%
11
#2560
0%
01
#2565
1%
11
0,
#2570
0%
01
#2575
1%
11
0-
#2580
0%
01
#2585
b100 >
1%
11
0.
#2590
0%
01
#2595
1"
1#
1$
1<
1%
11
#2600
0%
01
#2605
1%
11
b10111001 B
b10 @
b1111 A
1,
#2610
0%
01
#2615
1%
11
b10111001 E
b10 C
b1111 D
1-
#2620
0%
01
#2625
b0 >
1%
11
b10111001 H
b10 F
b1111 G
1.
#2630
0%
01
#2635
1!
1=
1%
11
#2640
0%
01
#2645
b1 >
1%
11
0)
#2650
0%
01
#2655
b1100010 ?
b0 &
b0 4
b0 '
b0 3
b0 (
b0 2
b0 ;
0!
0=
1%
11
#2660
0%
01
#2665
b10111001 ?
1%
11
b10111001 /
b10111001 5
#2670
0%
01
#2675
b10 >
1%
11
b10000 J
1)
#2680
0%
01
#2685
b101110 ?
b1 &
b1 4
b1 '
b1 3
b1 (
b1 2
b1 ;
1%
11
#2690
0%
01
#2695
b1011 ?
1%
11
#2700
0%
01
#2705
b10 ?
b10 &
b10 4
b10 '
b10 3
b10 (
b10 2
b10 ;
1%
11
#2710
0%
01
#2715
b0 ?
1%
11
#2720
0%
01
#2725
b11 >
1%
11
#2730
0%
01
#2735
0"
0#
0$
0<
1%
11
#2740
0%
01
#2745
1%
11
0,
#2750
0%
01
#2755
1%
11
0-
#2760
0%
01
#2765
b100 >
1%
11
0.
#2770
0%
01
#2775
1"
1#
1$
1<
1%
11
#2780
0%
01
#2785
1%
11
b10000 A
1,
#2790
0%
01
#2795
1%
11
b10000 D
1-
#2800
0%
01
#2805
b0 >
1%
11
b10000 G
1.
#2810
0%
01
#2815
1!
1=
1%
11
